{"data":[{"boxmean":true,"boxpoints":"all","customdata":[["CHI",2015,5843614.0,0,0,0,0,"Exclue des s\u00e9ries"],["COL",2015,5050909.0,0,0,0,0,"Exclue des s\u00e9ries"],["HOU",2015,5121708.0,0,0,0,0,"Exclue des s\u00e9ries"],["LAG",2015,21267575.0,0,0,0,0,"Exclue des s\u00e9ries"],["NE",2015,6516090.0,0,0,0,0,"Exclue des s\u00e9ries"],["NYCFC",2015,17414268.0,0,0,0,0,"Exclue des s\u00e9ries"],["ORL",2015,11290004.0,0,0,0,0,"Exclue des s\u00e9ries"],["PHI",2015,5408401.0,0,0,0,0,"Exclue des s\u00e9ries"],["RSL",2015,5436922.0,0,0,0,0,"Exclue des s\u00e9ries"],["SJ",2015,5332505.0,0,0,0,0,"Exclue des s\u00e9ries"],["SKC",2015,null,0,0,0,0,"Exclue des s\u00e9ries"],["TOR",2015,22136513.0,0,0,0,0,"Exclue des s\u00e9ries"],["CHI",2016,4303902.0,0,0,0,0,"Exclue des s\u00e9ries"],["CLB",2016,5574070.0,0,0,0,0,"Exclue des s\u00e9ries"],["DC",2016,5525668.0,0,0,0,0,"Exclue des s\u00e9ries"],["HOU",2016,5104169.0,0,0,0,0,"Exclue des s\u00e9ries"],["NE",2016,5878364.0,0,0,0,0,"Exclue des s\u00e9ries"],["ORL",2016,11753268.0,0,0,0,0,"Exclue des s\u00e9ries"],["PHI",2016,6402695.0,0,0,0,0,"Exclue des s\u00e9ries"],["POR",2016,7376217.0,0,0,0,0,"Exclue des s\u00e9ries"],["RSL",2016,6246491.0,0,0,0,0,"Exclue des s\u00e9ries"],["SJ",2016,7161825.0,0,0,0,0,"Exclue des s\u00e9ries"],["SKC",2016,null,0,0,0,0,"Exclue des s\u00e9ries"],["VAN",2016,6911820.0,0,0,0,0,"Exclue des s\u00e9ries"],["ATL",2017,9395516.0,0,0,0,0,"Exclue des s\u00e9ries"],["CHI",2017,13089574.0,0,0,0,0,"Exclue des s\u00e9ries"],["COL",2017,8256505.0,0,0,0,0,"Exclue des s\u00e9ries"],["DAL",2017,7345389.0,0,0,0,0,"Exclue des s\u00e9ries"],["DC",2017,5416549.0,0,0,0,0,"Exclue des s\u00e9ries"],["LAG",2017,14358893.0,0,0,0,0,"Exclue des s\u00e9ries"],["MIN",2017,5753434.0,0,0,0,0,"Exclue des s\u00e9ries"],["MTL",2017,6324616.0,0,0,0,0,"Exclue des s\u00e9ries"],["NE",2017,7477467.0,0,0,0,0,"Exclue des s\u00e9ries"],["ORL",2017,14534739.0,0,0,0,0,"Exclue des s\u00e9ries"],["PHI",2017,7114432.0,0,0,0,0,"Exclue des s\u00e9ries"],["RSL",2017,8569778.0,0,0,0,0,"Exclue des s\u00e9ries"],["SJ",2017,8381997.0,0,0,0,0,"Exclue des s\u00e9ries"],["SKC",2017,null,0,0,0,0,"Exclue des s\u00e9ries"],["CHI",2018,15531522.0,0,0,0,0,"Exclue des s\u00e9ries"],["COL",2018,9741571.0,0,0,0,0,"Exclue des s\u00e9ries"],["DAL",2018,9334556.0,0,0,0,0,"Exclue des s\u00e9ries"],["DC",2018,9689539.0,0,0,0,0,"Exclue des s\u00e9ries"],["HOU",2018,5896563.0,0,0,0,0,"Exclue des s\u00e9ries"],["LAFC",2018,14134137.0,0,0,0,0,"Exclue des s\u00e9ries"],["LAG",2018,17507010.0,0,0,0,0,"Exclue des s\u00e9ries"],["MIN",2018,8542122.0,0,0,0,0,"Exclue des s\u00e9ries"],["MTL",2018,12642037.0,0,0,0,0,"Exclue des s\u00e9ries"],["NE",2018,7471670.0,0,0,0,0,"Exclue des s\u00e9ries"],["ORL",2018,8873899.0,0,0,0,0,"Exclue des s\u00e9ries"],["PHI",2018,8914583.0,0,0,0,0,"Exclue des s\u00e9ries"],["SJ",2018,8308343.0,0,0,0,0,"Exclue des s\u00e9ries"],["TOR",2018,26559206.0,0,0,0,0,"Exclue des s\u00e9ries"],["VAN",2018,8107772.0,0,0,0,0,"Exclue des s\u00e9ries"],["CHI",2019,17114980.0,0,0,0,0,"Exclue des s\u00e9ries"],["CIN",2019,9564915.0,0,0,0,0,"Exclue des s\u00e9ries"],["CLB",2019,10614613.0,0,0,0,0,"Exclue des s\u00e9ries"],["COL",2019,8599995.0,0,0,0,0,"Exclue des s\u00e9ries"],["DAL",2019,8807319.0,0,0,0,0,"Exclue des s\u00e9ries"],["DC",2019,10195277.0,0,0,0,0,"Exclue des s\u00e9ries"],["HOU",2019,8744849.0,0,0,0,0,"Exclue des s\u00e9ries"],["MIN",2019,10632485.0,0,0,0,0,"Exclue des s\u00e9ries"],["MTL",2019,13152273.0,0,0,0,0,"Exclue des s\u00e9ries"],["NE",2019,10658219.0,0,0,0,0,"Exclue des s\u00e9ries"],["NYRB",2019,8668934.0,0,0,0,0,"Exclue des s\u00e9ries"],["ORL",2019,12573226.0,0,0,0,0,"Exclue des s\u00e9ries"],["POR",2019,12553916.0,0,0,0,0,"Exclue des s\u00e9ries"],["SJ",2019,10619981.0,0,0,0,0,"Exclue des s\u00e9ries"],["SKC",2019,null,0,0,0,0,"Exclue des s\u00e9ries"],["VAN",2019,8152130.0,0,0,0,0,"Exclue des s\u00e9ries"]],"hovertemplate":"%{customdata[0]} %{customdata[1]}<br>%{y:$,.0f}<br><extra></extra>","line":{"color":"grey"},"marker":{"color":"#19af54","size":4},"name":"","showlegend":false,"type":"box","whiskerwidth":0.2,"x":["Exclue des s\u00e9ries","Exclue des s\u00e9ries","Exclue des s\u00e9ries","Exclue des s\u00e9ries","Exclue des s\u00e9ries","Exclue des s\u00e9ries","Exclue des s\u00e9ries","Exclue des s\u00e9ries","Exclue des s\u00e9ries","Exclue des s\u00e9ries","Exclue des s\u00e9ries","Exclue des s\u00e9ries","Exclue des s\u00e9ries","Exclue des s\u00e9ries","Exclue des s\u00e9ries","Exclue des s\u00e9ries","Exclue des s\u00e9ries","Exclue des s\u00e9ries","Exclue des s\u00e9ries","Exclue des s\u00e9ries","Exclue des s\u00e9ries","Exclue des s\u00e9ries","Exclue des s\u00e9ries","Exclue des s\u00e9ries","Exclue des s\u00e9ries","Exclue des s\u00e9ries","Exclue des s\u00e9ries","Exclue des s\u00e9ries","Exclue des s\u00e9ries","Exclue des s\u00e9ries","Exclue des s\u00e9ries","Exclue des s\u00e9ries","Exclue des s\u00e9ries","Exclue des s\u00e9ries","Exclue des s\u00e9ries","Exclue des s\u00e9ries","Exclue des s\u00e9ries","Exclue des s\u00e9ries","Exclue des s\u00e9ries","Exclue des s\u00e9ries","Exclue des s\u00e9ries","Exclue des s\u00e9ries","Exclue des s\u00e9ries","Exclue des s\u00e9ries","Exclue des s\u00e9ries","Exclue des s\u00e9ries","Exclue des s\u00e9ries","Exclue des s\u00e9ries","Exclue des s\u00e9ries","Exclue des s\u00e9ries","Exclue des s\u00e9ries","Exclue des s\u00e9ries","Exclue des s\u00e9ries","Exclue des s\u00e9ries","Exclue des s\u00e9ries","Exclue des s\u00e9ries","Exclue des s\u00e9ries","Exclue des s\u00e9ries","Exclue des s\u00e9ries","Exclue des s\u00e9ries","Exclue des s\u00e9ries","Exclue des s\u00e9ries","Exclue des s\u00e9ries","Exclue des s\u00e9ries","Exclue des s\u00e9ries","Exclue des s\u00e9ries","Exclue des s\u00e9ries","Exclue des s\u00e9ries","Exclue des s\u00e9ries"],"y":[5843614.0,5050909.0,5121708.0,21267575.0,6516090.0,17414268.0,11290004.0,5408401.0,5436922.0,5332505.0,null,22136513.0,4303902.0,5574070.0,5525668.0,5104169.0,5878364.0,11753268.0,6402695.0,7376217.0,6246491.0,7161825.0,null,6911820.0,9395516.0,13089574.0,8256505.0,7345389.0,5416549.0,14358893.0,5753434.0,6324616.0,7477467.0,14534739.0,7114432.0,8569778.0,8381997.0,null,15531522.0,9741571.0,9334556.0,9689539.0,5896563.0,14134137.0,17507010.0,8542122.0,12642037.0,7471670.0,8873899.0,8914583.0,8308343.0,26559206.0,8107772.0,17114980.0,9564915.0,10614613.0,8599995.0,8807319.0,10195277.0,8744849.0,10632485.0,13152273.0,10658219.0,8668934.0,12573226.0,12553916.0,10619981.0,null,8152130.0]},{"boxmean":true,"boxpoints":"all","customdata":[["DC",2015,4286764.0,1,0,0,0,"Premi\u00e8re ronde"],["MTL",2015,6301788.0,1,0,0,0,"Premi\u00e8re ronde"],["SEA",2015,13288445.0,1,0,0,0,"Premi\u00e8re ronde"],["VAN",2015,6261095.0,1,0,0,0,"Premi\u00e8re ronde"],["DAL",2016,4742926.0,1,0,0,0,"Premi\u00e8re ronde"],["LAG",2016,18124236.0,1,0,0,0,"Premi\u00e8re ronde"],["NYCFC",2016,21313809.0,1,0,0,0,"Premi\u00e8re ronde"],["NYRB",2016,6317205.0,1,0,0,0,"Premi\u00e8re ronde"],["NYCFC",2017,18072632.0,1,0,0,0,"Premi\u00e8re ronde"],["NYRB",2017,7152063.0,1,0,0,0,"Premi\u00e8re ronde"],["POR",2017,11365316.0,1,0,0,0,"Premi\u00e8re ronde"],["VAN",2017,8441386.0,1,0,0,0,"Premi\u00e8re ronde"],["CLB",2018,7715954.0,1,0,0,0,"Premi\u00e8re ronde"],["NYCFC",2018,14824390.0,1,0,0,0,"Premi\u00e8re ronde"],["RSL",2018,8132416.0,1,0,0,0,"Premi\u00e8re ronde"],["SEA",2018,11777649.0,1,0,0,0,"Premi\u00e8re ronde"],["LAG",2019,19636980.0,1,0,0,0,"Premi\u00e8re ronde"],["NYCFC",2019,10415586.0,1,0,0,0,"Premi\u00e8re ronde"],["PHI",2019,9854737.0,1,0,0,0,"Premi\u00e8re ronde"],["RSL",2019,11117789.0,1,0,0,0,"Premi\u00e8re ronde"]],"hovertemplate":"%{customdata[0]} %{customdata[1]}<br>%{y:$,.0f}<br><extra></extra>","line":{"color":"grey"},"marker":{"color":"#19af54","size":4},"name":"","showlegend":false,"type":"box","whiskerwidth":0.2,"x":["Premi\u00e8re ronde","Premi\u00e8re ronde","Premi\u00e8re ronde","Premi\u00e8re ronde","Premi\u00e8re ronde","Premi\u00e8re ronde","Premi\u00e8re ronde","Premi\u00e8re ronde","Premi\u00e8re ronde","Premi\u00e8re ronde","Premi\u00e8re ronde","Premi\u00e8re ronde","Premi\u00e8re ronde","Premi\u00e8re ronde","Premi\u00e8re ronde","Premi\u00e8re ronde","Premi\u00e8re ronde","Premi\u00e8re ronde","Premi\u00e8re ronde","Premi\u00e8re ronde"],"y":[4286764.0,6301788.0,13288445.0,6261095.0,4742926.0,18124236.0,21313809.0,6317205.0,18072632.0,7152063.0,11365316.0,8441386.0,7715954.0,14824390.0,8132416.0,11777649.0,19636980.0,10415586.0,9854737.0,11117789.0]},{"boxmean":true,"boxpoints":"all","customdata":[["DAL",2015,4098292.0,1,1,0,0,"Deuxi\u00e8me Ronde"],["NYRB",2015,4229937.0,1,1,0,0,"Deuxi\u00e8me Ronde"],["COL",2016,8662788.0,1,1,0,0,"Deuxi\u00e8me Ronde"],["MTL",2016,6962510.0,1,1,0,0,"Deuxi\u00e8me Ronde"],["CLB",2017,6771046.0,1,1,0,0,"Deuxi\u00e8me Ronde"],["HOU",2017,5771646.0,1,1,0,0,"Deuxi\u00e8me Ronde"],["NYRB",2018,8064993.0,1,1,0,0,"Deuxi\u00e8me Ronde"],["SKC",2018,null,1,1,0,0,"Deuxi\u00e8me Ronde"],["ATL",2019,12957119.0,1,1,0,0,"Deuxi\u00e8me Ronde"],["LAFC",2019,13769952.0,1,1,0,0,"Deuxi\u00e8me Ronde"]],"hovertemplate":"%{customdata[0]} %{customdata[1]}<br>%{y:$,.0f}<br><extra></extra>","line":{"color":"grey"},"marker":{"color":"#19af54","size":4},"name":"","showlegend":false,"type":"box","whiskerwidth":0.2,"x":["Deuxi\u00e8me Ronde","Deuxi\u00e8me Ronde","Deuxi\u00e8me Ronde","Deuxi\u00e8me Ronde","Deuxi\u00e8me Ronde","Deuxi\u00e8me Ronde","Deuxi\u00e8me Ronde","Deuxi\u00e8me Ronde","Deuxi\u00e8me Ronde","Deuxi\u00e8me Ronde"],"y":[4098292.0,4229937.0,8662788.0,6962510.0,6771046.0,5771646.0,8064993.0,null,12957119.0,13769952.0]},{"boxmean":true,"boxpoints":"all","customdata":[["CLB",2015,5745125.0,1,1,1,0,"Finale"],["POR",2015,6052908.0,1,1,1,1,"Finale"],["SEA",2016,12445317.0,1,1,1,1,"Finale"],["TOR",2016,21529800.0,1,1,1,0,"Finale"],["SEA",2017,11820250.0,1,1,1,0,"Finale"],["TOR",2017,22521442.0,1,1,1,1,"Finale"],["ATL",2018,11606330.0,1,1,1,1,"Finale"],["POR",2018,10994793.0,1,1,1,0,"Finale"],["SEA",2019,13678414.0,1,1,1,1,"Finale"],["TOR",2019,24267067.0,1,1,1,0,"Finale"]],"hovertemplate":"%{customdata[0]} %{customdata[1]}<br>%{y:$,.0f}<br><extra></extra>","line":{"color":"grey"},"marker":{"color":"#19af54","size":4},"name":"","showlegend":false,"type":"box","whiskerwidth":0.2,"x":["Finale","Finale","Finale","Finale","Finale","Finale","Finale","Finale","Finale","Finale"],"y":[5745125.0,6052908.0,12445317.0,21529800.0,11820250.0,22521442.0,11606330.0,10994793.0,13678414.0,24267067.0]}],"layout":{"font":{"color":"black"},"paper_bgcolor":"#eeeeee","plot_bgcolor":"#eeeeee","showlegend":false,"template":{"data":{"bar":[{"error_x":{"color":"#2a3f5f"},"error_y":{"color":"#2a3f5f"},"marker":{"line":{"color":"#E5ECF6","width":0.5}},"type":"bar"}],"barpolar":[{"marker":{"line":{"color":"#E5ECF6","width":0.5}},"type":"barpolar"}],"carpet":[{"aaxis":{"endlinecolor":"#2a3f5f","gridcolor":"white","linecolor":"white","minorgridcolor":"white","startlinecolor":"#2a3f5f"},"baxis":{"endlinecolor":"#2a3f5f","gridcolor":"white","linecolor":"white","minorgridcolor":"white","startlinecolor":"#2a3f5f"},"type":"carpet"}],"choropleth":[{"colorbar":{"outlinewidth":0,"ticks":""},"type":"choropleth"}],"contour":[{"colorbar":{"outlinewidth":0,"ticks":""},"colorscale":[[0.0,"#0d0887"],[0.1111111111111111,"#46039f"],[0.2222222222222222,"#7201a8"],[0.3333333333333333,"#9c179e"],[0.4444444444444444,"#bd3786"],[0.5555555555555556,"#d8576b"],[0.6666666666666666,"#ed7953"],[0.7777777777777778,"#fb9f3a"],[0.8888888888888888,"#fdca26"],[1.0,"#f0f921"]],"type":"contour"}],"contourcarpet":[{"colorbar":{"outlinewidth":0,"ticks":""},"type":"contourcarpet"}],"heatmap":[{"colorbar":{"outlinewidth":0,"ticks":""},"colorscale":[[0.0,"#0d0887"],[0.1111111111111111,"#46039f"],[0.2222222222222222,"#7201a8"],[0.3333333333333333,"#9c179e"],[0.4444444444444444,"#bd3786"],[0.5555555555555556,"#d8576b"],[0.6666666666666666,"#ed7953"],[0.7777777777777778,"#fb9f3a"],[0.8888888888888888,"#fdca26"],[1.0,"#f0f921"]],"type":"heatmap"}],"heatmapgl":[{"colorbar":{"outlinewidth":0,"ticks":""},"colorscale":[[0.0,"#0d0887"],[0.1111111111111111,"#46039f"],[0.2222222222222222,"#7201a8"],[0.3333333333333333,"#9c179e"],[0.4444444444444444,"#bd3786"],[0.5555555555555556,"#d8576b"],[0.6666666666666666,"#ed7953"],[0.7777777777777778,"#fb9f3a"],[0.8888888888888888,"#fdca26"],[1.0,"#f0f921"]],"type":"heatmapgl"}],"histogram":[{"marker":{"colorbar":{"outlinewidth":0,"ticks":""}},"type":"histogram"}],"histogram2d":[{"colorbar":{"outlinewidth":0,"ticks":""},"colorscale":[[0.0,"#0d0887"],[0.1111111111111111,"#46039f"],[0.2222222222222222,"#7201a8"],[0.3333333333333333,"#9c179e"],[0.4444444444444444,"#bd3786"],[0.5555555555555556,"#d8576b"],[0.6666666666666666,"#ed7953"],[0.7777777777777778,"#fb9f3a"],[0.8888888888888888,"#fdca26"],[1.0,"#f0f921"]],"type":"histogram2d"}],"histogram2dcontour":[{"colorbar":{"outlinewidth":0,"ticks":""},"colorscale":[[0.0,"#0d0887"],[0.1111111111111111,"#46039f"],[0.2222222222222222,"#7201a8"],[0.3333333333333333,"#9c179e"],[0.4444444444444444,"#bd3786"],[0.5555555555555556,"#d8576b"],[0.6666666666666666,"#ed7953"],[0.7777777777777778,"#fb9f3a"],[0.8888888888888888,"#fdca26"],[1.0,"#f0f921"]],"type":"histogram2dcontour"}],"mesh3d":[{"colorbar":{"outlinewidth":0,"ticks":""},"type":"mesh3d"}],"parcoords":[{"line":{"colorbar":{"outlinewidth":0,"ticks":""}},"type":"parcoords"}],"pie":[{"automargin":true,"type":"pie"}],"scatter":[{"marker":{"colorbar":{"outlinewidth":0,"ticks":""}},"type":"scatter"}],"scatter3d":[{"line":{"colorbar":{"outlinewidth":0,"ticks":""}},"marker":{"colorbar":{"outlinewidth":0,"ticks":""}},"type":"scatter3d"}],"scattercarpet":[{"marker":{"colorbar":{"outlinewidth":0,"ticks":""}},"type":"scattercarpet"}],"scattergeo":[{"marker":{"colorbar":{"outlinewidth":0,"ticks":""}},"type":"scattergeo"}],"scattergl":[{"marker":{"colorbar":{"outlinewidth":0,"ticks":""}},"type":"scattergl"}],"scattermapbox":[{"marker":{"colorbar":{"outlinewidth":0,"ticks":""}},"type":"scattermapbox"}],"scatterpolar":[{"marker":{"colorbar":{"outlinewidth":0,"ticks":""}},"type":"scatterpolar"}],"scatterpolargl":[{"marker":{"colorbar":{"outlinewidth":0,"ticks":""}},"type":"scatterpolargl"}],"scatterternary":[{"marker":{"colorbar":{"outlinewidth":0,"ticks":""}},"type":"scatterternary"}],"surface":[{"colorbar":{"outlinewidth":0,"ticks":""},"colorscale":[[0.0,"#0d0887"],[0.1111111111111111,"#46039f"],[0.2222222222222222,"#7201a8"],[0.3333333333333333,"#9c179e"],[0.4444444444444444,"#bd3786"],[0.5555555555555556,"#d8576b"],[0.6666666666666666,"#ed7953"],[0.7777777777777778,"#fb9f3a"],[0.8888888888888888,"#fdca26"],[1.0,"#f0f921"]],"type":"surface"}],"table":[{"cells":{"fill":{"color":"#EBF0F8"},"line":{"color":"white"}},"header":{"fill":{"color":"#C8D4E3"},"line":{"color":"white"}},"type":"table"}]},"layout":{"annotationdefaults":{"arrowcolor":"#2a3f5f","arrowhead":0,"arrowwidth":1},"autotypenumbers":"strict","coloraxis":{"colorbar":{"outlinewidth":0,"ticks":""}},"colorscale":{"diverging":[[0,"#8e0152"],[0.1,"#c51b7d"],[0.2,"#de77ae"],[0.3,"#f1b6da"],[0.4,"#fde0ef"],[0.5,"#f7f7f7"],[0.6,"#e6f5d0"],[0.7,"#b8e186"],[0.8,"#7fbc41"],[0.9,"#4d9221"],[1,"#276419"]],"sequential":[[0.0,"#0d0887"],[0.1111111111111111,"#46039f"],[0.2222222222222222,"#7201a8"],[0.3333333333333333,"#9c179e"],[0.4444444444444444,"#bd3786"],[0.5555555555555556,"#d8576b"],[0.6666666666666666,"#ed7953"],[0.7777777777777778,"#fb9f3a"],[0.8888888888888888,"#fdca26"],[1.0,"#f0f921"]],"sequentialminus":[[0.0,"#0d0887"],[0.1111111111111111,"#46039f"],[0.2222222222222222,"#7201a8"],[0.3333333333333333,"#9c179e"],[0.4444444444444444,"#bd3786"],[0.5555555555555556,"#d8576b"],[0.6666666666666666,"#ed7953"],[0.7777777777777778,"#fb9f3a"],[0.8888888888888888,"#fdca26"],[1.0,"#f0f921"]]},"colorway":["#636efa","#EF553B","#00cc96","#ab63fa","#FFA15A","#19d3f3","#FF6692","#B6E880","#FF97FF","#FECB52"],"font":{"color":"#2a3f5f"},"geo":{"bgcolor":"white","lakecolor":"white","landcolor":"#E5ECF6","showlakes":true,"showland":true,"subunitcolor":"white"},"hoverlabel":{"align":"left"},"hovermode":"closest","mapbox":{"style":"light"},"paper_bgcolor":"white","plot_bgcolor":"#E5ECF6","polar":{"angularaxis":{"gridcolor":"white","linecolor":"white","ticks":""},"bgcolor":"#E5ECF6","radialaxis":{"gridcolor":"white","linecolor":"white","ticks":""}},"scene":{"xaxis":{"backgroundcolor":"#E5ECF6","gridcolor":"white","gridwidth":2,"linecolor":"white","showbackground":true,"ticks":"","zerolinecolor":"white"},"yaxis":{"backgroundcolor":"#E5ECF6","gridcolor":"white","gridwidth":2,"linecolor":"white","showbackground":true,"ticks":"","zerolinecolor":"white"},"zaxis":{"backgroundcolor":"#E5ECF6","gridcolor":"white","gridwidth":2,"linecolor":"white","showbackground":true,"ticks":"","zerolinecolor":"white"}},"shapedefaults":{"line":{"color":"#2a3f5f"}},"ternary":{"aaxis":{"gridcolor":"white","linecolor":"white","ticks":""},"baxis":{"gridcolor":"white","linecolor":"white","ticks":""},"bgcolor":"#E5ECF6","caxis":{"gridcolor":"white","linecolor":"white","ticks":""}},"title":{"x":0.05},"xaxis":{"automargin":true,"gridcolor":"white","linecolor":"white","ticks":"","title":{"standoff":15},"zerolinecolor":"white","zerolinewidth":2},"yaxis":{"automargin":true,"gridcolor":"white","linecolor":"white","ticks":"","title":{"standoff":15},"zerolinecolor":"white","zerolinewidth":2}}},"xaxis":{"zeroline":false},"yaxis":{"zeroline":false}}}